startfastapi/__init__.py
startfastapi/__main__.py
startfastapi/config.py
startfastapi/context.py
startfastapi/generator.py
startfastapi/main.py
startfastapi/templates/__init__.py
startfastapi/templates/app/__init__.py
startfastapi/templates/app/cookiecutter.json
startfastapi/templates/app/{{ cookiecutter.folder_name }}/models.py
startfastapi/templates/app/{{ cookiecutter.folder_name }}/schemas.py
startfastapi/templates/app/{{ cookiecutter.folder_name }}/services.py
startfastapi/templates/app/{{ cookiecutter.folder_name }}/views.py
startfastapi/templates/project/__init__.py
startfastapi/templates/project/cookiecutter.json
startfastapi/templates/project/{{ cookiecutter.folder_name }}/.env-example
startfastapi/templates/project/{{ cookiecutter.folder_name }}/.gitignore
startfastapi/templates/project/{{ cookiecutter.folder_name }}/README.md
startfastapi/templates/project/{{ cookiecutter.folder_name }}/gunicorn.py
startfastapi/templates/project/{{ cookiecutter.folder_name }}/main.py
startfastapi/templates/project/{{ cookiecutter.folder_name }}/requirements.txt
startfastapi/templates/project/{{ cookiecutter.folder_name }}/src/apis/__init__.py
startfastapi/templates/project/{{ cookiecutter.folder_name }}/src/apis/deps.py
startfastapi/templates/project/{{ cookiecutter.folder_name }}/src/apis/model.py
startfastapi/templates/project/{{ cookiecutter.folder_name }}/src/apis/schema.py
startfastapi/templates/project/{{ cookiecutter.folder_name }}/src/apis/service.py
startfastapi/templates/project/{{ cookiecutter.folder_name }}/src/apis/user/models.py
startfastapi/templates/project/{{ cookiecutter.folder_name }}/src/apis/user/schemas.py
startfastapi/templates/project/{{ cookiecutter.folder_name }}/src/apis/user/services.py
startfastapi/templates/project/{{ cookiecutter.folder_name }}/src/apis/user/views.py
startfastapi/templates/project/{{ cookiecutter.folder_name }}/src/core/app.py
startfastapi/templates/project/{{ cookiecutter.folder_name }}/src/core/config.py
startfastapi-0.1.3.dist-info/LICENSE
startfastapi-0.1.3.dist-info/METADATA
startfastapi-0.1.3.dist-info/WHEEL
startfastapi-0.1.3.dist-info/entry_points.txt
startfastapi-0.1.3.dist-info/RECORD
