Metadata-Version: 2.1
Name: startfastapi
Version: 0.1.3
Summary: Managing FastAPI projects made easy.
Home-page: https://github.com/hiyoung123/startfastapi
License: MIT
Author: hiyoung
Author-email: hiyoungliu@gmail.com
Requires-Python: >=3.10,<4.0
Classifier: License :: OSI Approved :: MIT License
Classifier: Programming Language :: Python :: 3
Classifier: Programming Language :: Python :: 3.10
Classifier: Programming Language :: Python :: 3.11
Classifier: Programming Language :: Python :: 3.12
Requires-Dist: cookiecutter (>=2.6.0)
Requires-Dist: pydantic (>=2.8.2)
Requires-Dist: typer (>=0.12.3)
Project-URL: Repository, https://github.com/hiyoung123/startfastapi
